maintenance_utils/__init__.py
maintenance_utils/calculate_next_service.py
maintenance_utils/count_records.py
maintenance_utils/count_upcoming_maintenance.py
maintenance_utils/report_generation.py
maintenance_utils/sort_records_by_date.py
maintenance_utils-0.1.1.dist-info/LICENSE
maintenance_utils-0.1.1.dist-info/METADATA
maintenance_utils-0.1.1.dist-info/WHEEL
maintenance_utils-0.1.1.dist-info/top_level.txt
maintenance_utils-0.1.1.dist-info/RECORD
