Metadata-Version: 2.1
Name: maintenance_utils
Version: 0.1.1
Summary: Utility functions for vehicle service scheduling
Author: Ajay Panwar
Author-email: ajay.gemini90@gmail.com
Classifier: Programming Language :: Python :: 3
Classifier: License :: OSI Approved :: MIT License
Classifier: Operating System :: OS Independent
Requires-Python: >=3.6
License-File: LICENSE
